{
  "name": "WTM Madrid",
  "localtion": "Google Campus",
  "days": [
    {
      "dayId": 1,
      "date": "07/03/2020",
      "tracks": [
        {
          "name": "Track 1",
          "location": "Auditorio",
          "talks": [
            {
              "position": 0,
              "speaker": "",
              "speakerInfo": "",
              "title": "Registro",
              "description": "",
              "startTime": "09:30",
              "endTime": "10:00"
            },
            {
              "position": 1,
              "speaker": "",
              "speakerInfo": "",
              "title": "Bienvenida",
              "description": "",
              "startTime": "10:00",
              "endTime": "10:15"
            },
            {
              "position": 2,
              "speaker": "Clara Luis Mingueza",
              "speakerInfo": "",
              "title": "Generación musical con redes neuronales",
              "description": "",
              "startTime": "10:25",
              "endTime": "11:10"
            },
            {
              "position": 3,
              "speaker": "Elisa Cabana Garcereran de Vall",
              "speakerInfo": "",
              "title": "Inteligencia Artificial para aprender Lengua de Signos",
              "description": "",
              "startTime": "11:20",
              "endTime": "11:45"
            },
            {
              "position": 4,
              "speaker": "",
              "speakerInfo": "",
              "title": "Desayuno",
              "description": "",
              "startTime": "11:45",
              "endTime": "12:15"
            },
            {
              "position": 5,
              "speaker": "Carolina Gómez Uriarte y Marta Barrio",
              "speakerInfo": "",
              "title": "2FA? Trust me, I've pwned you",
              "description": "",
              "startTime": "12:15",
              "endTime": "13:00"
            },
            {
              "position": 5,
              "speaker": "Laura morales Díez",
              "speakerInfo": "",
              "title": "Futuros posibles con Realidad extendida",
              "description": "",
              "startTime": "13:10",
              "endTime": "14:00"
            },
            {
              "position": 6,
              "speaker": "",
              "speakerInfo": "",
              "title": "Comida",
              "description": "",
              "startTime": "14:00",
              "endTime": "15:15"
            },
            {
              "position": 7,
              "speaker": "Ana Laguna",
              "speakerInfo": "",
              "title": "Baby crying translation with Deep Learning",
              "description": "",
              "startTime": "15:15",
              "endTime": "15:40"
            },{
              "position": 8,
              "speaker": "Débora Gómez Bertoli",
              "speakerInfo": "",
              "title": "El Flutter de Hamelín",
              "description": "",
              "startTime": "15:50",
              "endTime": "16:35"
            },{
              "position": 9,
              "speaker": "Nuria Prieto Pinedo",
              "speakerInfo": "",
              "title": "Anillo Tuitero",
              "description": "",
              "startTime": "16:45",
              "endTime": "17:10"
            },
            {
              "position": 10,
              "speaker": "",
              "speakerInfo": "",
              "title": "Cierre y sorteos",
              "description": "",
              "startTime": "17:20",
              "endTime": "18:00"
            }
          ]
        },
        {
          "name": "Track 2",
          "location": "Sala MEETUP",
          "talks": [
            {
              "position": 0,
              "speaker": "",
              "speakerInfo": "",
              "title": "",
              "description": "",
              "startTime": "09:30",
              "endTime": "10:00"
            },
            {
              "position": 1,
              "speaker": "",
              "speakerInfo": "",
              "title": "",
              "description": "",
              "startTime": "10:00",
              "endTime": "10:15"
            },
            {
              "position": 2,
              "speaker": "Meriem El Yamri",
              "speakerInfo": "",
              "title": "Hola, Kubernetes!",
              "description": "",
              "startTime": "10:25",
              "endTime": "11:10"
            },
            {
              "position": 3,
              "speaker": "Jimena Catalina Gayo",
              "speakerInfo": "",
              "title": "Como terminar un side project y no abandonarlo en la cuneta",
              "description": "",
              "startTime": "11:20",
              "endTime": "11:45"
            },
            {
              "position": 4,
              "speaker": "",
              "speakerInfo": "",
              "title": "Desayuno",
              "description": "",
              "startTime": "11:45",
              "endTime": "12:15"
            },
            {
              "position": 5,
              "speaker": "María Medina",
              "speakerInfo": "",
              "title": "Aprende teoría de grafos con las tramas de corrupción en España",
              "description": "",
              "startTime": "12:15",
              "endTime": "13:00"
            },
            {
              "position": 5,
              "speaker": "Marta Arcones",
              "speakerInfo": "",
              "title": "Gestionando infraestructura en la nube con Terraform",
              "description": "",
              "startTime": "13:10",
              "endTime": "14:00"
            },
            {
              "position": 6,
              "speaker": "",
              "speakerInfo": "",
              "title": "Comida",
              "description": "",
              "startTime": "14:00",
              "endTime": "15:15"
            },
            {
              "position": 7,
              "speaker": "Teba Gómez",
              "speakerInfo": "",
              "title": "Asynchrony from the roots",
              "description": "",
              "startTime": "15:15",
              "endTime": "15:40"
            },{
              "position": 8,
              "speaker": "Maritere Nieto Galán",
              "speakerInfo": "",
              "title": "¿De verdad necesitas Blockchain?",
              "description": "",
              "startTime": "15:50",
              "endTime": "16:35"
            },{
              "position": 9,
              "speaker": "Bea Hernández",
              "speakerInfo": "",
              "title": "De qué hablamos cuando hablamos de Escher",
              "description": "",
              "startTime": "16:45",
              "endTime": "17:10"
            },
            {
              "position": 10,
              "speaker": "",
              "speakerInfo": "",
              "title": "Cierre y sorteos",
              "description": "",
              "startTime": "17:20",
              "endTime": "18:00"
            }
          ]
        }
      ]
    }
  ]
}
